<?xml version="1.0" encoding="UTF-8"?>
<sceneManager>

	<gameName>My game engine</gameName>
	
	<defaultScreenSize>
		<width>960</width>
		<height>720</height>
		<!--
			se mai poate pune si:
			<fullscreen />
		-->
	</defaultScreenSize>
	
	<backgroundColor>
		<r>0.1</r>
		<g>0.1</g>
		<b>0.1</b>
	</backgroundColor>
	
	<fog>
		<r>700</r>
		<R>1000</R>
		<color>
			<r>0.41</r>
			<g>0.44</g>
			<b>0.49</b>
		</color>
	</fog>

	<controls>

		<control>
			<key>A</key>
			<action>MOVE_CAMERA_POSITIVE_X</action>
		</control>
		<control>
			<key>D</key>
			<action>MOVE_CAMERA_NEGATIVE_X</action>
		</control>

		<control>
			<key>Q</key>
			<action>MOVE_CAMERA_POSITIVE_Y</action>
		</control>
		<control>
			<key>E</key>
			<action>MOVE_CAMERA_NEGATIVE_Y</action>
		</control>
		
		<control>
			<key>W</key>
			<action>MOVE_CAMERA_POSITIVE_Z</action>
		</control>
		<control>
			<key>S</key>
			<action>MOVE_CAMERA_NEGATIVE_Z</action>
		</control>

		<control>
			<key>&#38;</key>
			<action>ROTATE_CAMERA_POSITIVE_X</action>
		</control>
		<control>
			<key>(</key>
			<action>ROTATE_CAMERA_NEGATIVE_X</action>
		</control>

		<control>
			<key>%</key>
			<action>ROTATE_CAMERA_POSITIVE_Y</action>
		</control>
		<control>
			<key>&#39;</key>
			<action>ROTATE_CAMERA_NEGATIVE_Y</action>
		</control>

		<control>
			<key>O</key>
			<action>ROTATE_CAMERA_POSITIVE_Z</action>
		</control>
		<control>
			<key>P</key>
			<action>ROTATE_CAMERA_NEGATIVE_Z</action>
		</control>
		
		<!-- TODO : adaugati restul -->
	</controls>
	
	<cameras>
		<camera id="1">
			<comment>elemntul type este folosit doar in taskul optional cu tipurile de Camera </comment>
			<type>firstPerson</type>
			<position>
				<x>0</x>
				<y>0</y>
				<z>-500</z>
			</position>
			<target>
				<x>0</x>
				<y>0</y>
				<z>0</z>
			</target>
			<up>
				<x>0</x>
				<y>1</y>
				<z>0</z>
			</up>
			<translationSpeed>100</translationSpeed>
			<rotationSpeed>1</rotationSpeed>
			<fov>45</fov>
			<near>0.2</near>
			<far>100000</far>
		</camera>
		<!-- eventual si alte cameras -->
	</cameras>
	<activeCamera>1</activeCamera>

	
	<objects>
		
		<object id="1">
			<model>1</model>
			<shader>10</shader>
			<type>normal</type>
			<name>Crocodil_verde</name>
			<textures>
				<texture id="4"/>
			</textures>
			<position>
				<x>20.5</x>
				<y>27</y>
				<z>21.22</z>
			</position>
			<rotation>
				<x>0.5</x>
				<y>1.4</y>
				<z>1</z>
			</rotation>
			<scale>
				<x>1.0</x>
				<y>1.0</y>
				<z>1.0</z>
			</scale>
		</object>

		<object id="2">
			<model>1</model>
			<shader>10</shader>
			<type>normal</type>
			<name>Crocodil_verde_2</name>
			<textures>
				<texture id="4"/>
			</textures>
			<position>
				<x>-150.5</x>
				<y>27</y>
				<z>21.22</z>
			</position>
			<rotation>
				<x>0</x>
				<y>0</y>
				<z>0</z>
			</rotation>
			<scale>
				<x>1.0</x>
				<y>1.0</y>
				<z>1.0</z>
			</scale>
		</object>

		<object id="3">
			<model>2</model>
			<shader>10</shader>
			<type>normal</type>
			<name>Bus</name>
			<textures>
				<texture id="2"/>
			</textures>
			<position>
				<x>-70.5</x>
				<y>80</y>
				<z>90.22</z>
			</position>
			<rotation>
				<x>0</x>
				<y>0</y>
				<z>0</z>
			</rotation>
			<scale>
				<x>1.0</x>
				<y>1.0</y>
				<z>1.0</z>
			</scale>
			<followingCamera>
				<ox/>
				<oy/>
				<oz/>
			</followingCamera>
		</object>

		<object id="4">
			<model>10</model>
			<shader>10</shader>
			<type>normal</type>
			<name>Goliath</name>
			<textures>
				<texture id="1"/>
			</textures>
			<position>
				<x>-350.5</x>
				<y>27.0</y>
				<z>-200.0</z>
			</position>
			<rotation>
				<x>0</x>
				<y>0</y>
				<z>0</z>
			</rotation>
			<scale>
				<x>0.1</x>
				<y>0.1</y>
				<z>0.1</z>
			</scale>
		</object>

		<object id="5">
			<model>11</model>
			<shader>10</shader>
			<type>normal</type>
			<name>House</name>
			<textures>
				<texture id="3"/>
			</textures>
			<position>
				<x>450.5</x>
				<y>27.0</y>
				<z>200.0</z>
			</position>
			<rotation>
				<x>0</x>
				<y>0</y>
				<z>0</z>
			</rotation>
			<scale>
				<x>0.1</x>
				<y>0.1</y>
				<z>0.1</z>
			</scale>
		</object>

		<object id="6">
			<model>12</model>
			<shader>10</shader>
			<type>normal</type>
			<name>Marine</name>
			<textures>
				<texture id="5"/>
			</textures>
			<position>
				<x>-200.0</x>
				<y>-50.0</y>
				<z>-400.0</z>
			</position>
			<rotation>
				<x>0</x>
				<y>0</y>
				<z>0</z>
			</rotation>
			<scale>
				<x>1.0</x>
				<y>1.0</y>
				<z>1.0</z>
			</scale>
		</object>

		<object id="7">
			<model>13</model>
			<shader>10</shader>
			<type>normal</type>
			<name>Witch</name>
			<textures>
				<texture id="6"/>
			</textures>
			<position>
				<x>-200.0</x>
				<y>-20.0</y>
				<z>-500.0</z>
			</position>
			<rotation>
				<x>0</x>
				<y>0</y>
				<z>0</z>
			</rotation>
			<scale>
				<x>0.2</x>
				<y>0.2</y>
				<z>0.2</z>
			</scale>
		</object>

		<object id="8">
			<model>14</model>
			<shader>10</shader>
			<type>normal</type>
			<name>Woman1</name>
			<textures>
				<texture id="7"/>
			</textures>
			<position>
				<x>-200.0</x>
				<y>-50.0</y>
				<z>-600.0</z>
			</position>
			<rotation>
				<x>0</x>
				<y>0</y>
				<z>0</z>
			</rotation>
			<scale>
				<x>50.0</x>
				<y>50.0</y>
				<z>50.0</z>
			</scale>
		</object>

		<object id="9">
			<model>15</model>
			<shader>10</shader>
			<type>normal</type>
			<name>Woman2</name>
			<textures>
				<texture id="8"/>
			</textures>
			<position>
				<x>-200.0</x>
				<y>-50.0</y>
				<z>-700.0</z>
			</position>
			<rotation>
				<x>0</x>
				<y>0</y>
				<z>0</z>
			</rotation>
			<scale>
				<x>50.0</x>
				<y>50.0</y>
				<z>50.0</z>
			</scale>
		</object>

		<object id="10">
			<model>16</model>
			<shader>10</shader>
			<type>normal</type>
			<name>SCV</name>
			<textures>
				<texture id="9"/>
			</textures>
			<position>
				<x>-400.0</x>
				<y>-50.0</y>
				<z>-400.0</z>
			</position>
			<rotation>
				<x>0</x>
				<y>0</y>
				<z>0</z>
			</rotation>
			<scale>
				<x>0.3</x>
				<y>0.3</y>
				<z>0.3</z>
			</scale>
		</object>

		<object id="11">
			<model>17</model>
			<shader>10</shader>
			<type>normal</type>
			<name>train</name>
			<textures>
				<texture id="10"/>
			</textures>
			<position>
				<x>-400.0</x>
				<y>-30.0</y>
				<z>-600.0</z>
			</position>
			<rotation>
				<x>0</x>
				<y>0</y>
				<z>0</z>
			</rotation>
			<scale>
				<x>0.3</x>
				<y>0.3</y>
				<z>0.3</z>
			</scale>
		</object>

		<object id="12">
			<model>18</model>
			<shader>10</shader>
			<type>normal</type>
			<name>Command_Center</name>
			<textures>
				<texture id="11"/>
			</textures>
			<position>
				<x>-400.0</x>
				<y>-30.0</y>
				<z>-800.0</z>
			</position>
			<rotation>
				<x>0</x>
				<y>0</y>
				<z>0</z>
			</rotation>
			<scale>
				<x>0.3</x>
				<y>0.3</y>
				<z>0.3</z>
			</scale>
		</object>

		<object id="40">
			<model>5</model>
			<shader>11</shader>
			<type>normal</type>
			<name>Mesh_minge</name>
			<wired/>
			<color>
				<r>1.0</r>
				<g>0.0</g>
				<b>0.0</b>
			</color>
			<position>
				<x>3.5</x>
				<y>130</y>
				<z>50</z>
			</position>
			<rotation>
				<x>0</x>
				<y>0</y>
				<z>0</z>
			</rotation>
			<scale>
				<x>1.0</x>
				<y>1.0</y>
				<z>1.0</z>
			</scale>
		</object>
		
		<object id="41">
			<model>5</model>
			<shader>13</shader>
			<type>normal</type>
			<name>PhongSphere_1</name>
			<color>
				<r>0.4</r>
				<g>0.3</g>
				<b>0.0</b>
			</color>
			<textures>
				<texture id="40"/>
			</textures>
			<position>
				<x>190</x>
				<y>-20</y>
				<z>-220</z>
			</position>
			<rotation>
				<x>0.0</x>
				<y>0.0</y>
				<z>0.0</z>
			</rotation>
			<scale>
				<x>0.3</x>
				<y>0.3</y>
				<z>0.3</z>
			</scale>
			<lights>
				<light>1</light>
				<light>10</light>
				<light>100</light>
			</lights>
		</object>

		<object id="42">
			<model>5</model>
			<shader>12</shader>
			<type>normal</type>
			<name>PhongSphere_2</name>
			<color>
				<r>0.0</r>
				<g>0.3</g>
				<b>0.4</b>
			</color>
			<position>
				<x>190</x>
				<y>-20</y>
				<z>-270</z>
			</position>
			<rotation>
				<x>0.0</x>
				<y>0.0</y>
				<z>0.0</z>
			</rotation>
			<scale>
				<x>0.3</x>
				<y>0.3</y>
				<z>0.3</z>
			</scale>
			<lights>
				<light>1</light>
				<light>10</light>
				<light>100</light>
			</lights>
		</object>

		<object id="43">
			<model>5</model>
			<shader>12</shader>
			<type>normal</type>
			<name>PhongSphere_3</name>
			<color>
				<r>0.0</r>
				<g>0.3</g>
				<b>0.4</b>
			</color>
			<position>
				<x>190</x>
				<y>-20</y>
				<z>-320</z>
			</position>
			<rotation>
				<x>0.0</x>
				<y>0.0</y>
				<z>0.0</z>
			</rotation>
			<scale>
				<x>0.3</x>
				<y>0.3</y>
				<z>0.3</z>
			</scale>
			<lights>
				<light>1</light>
				<light>10</light>
				<light>100</light>
			</lights>
		</object>

		<object id="44">
			<model>5</model>
			<shader>12</shader>
			<type>normal</type>
			<name>PhongSphere_4</name>
			<color>
				<r>0.0</r>
				<g>0.3</g>
				<b>0.4</b>
			</color>
			<position>
				<x>190</x>
				<y>-20</y>
				<z>-370</z>
			</position>
			<rotation>
				<x>0.0</x>
				<y>0.0</y>
				<z>0.0</z>
			</rotation>
			<scale>
				<x>0.3</x>
				<y>0.3</y>
				<z>0.3</z>
			</scale>
			<lights>
				<light>1</light>
				<light>10</light>
				<light>100</light>
			</lights>
		</object>

		<object id="45">
			<model>5</model>
			<shader>12</shader>
			<type>normal</type>
			<name>PhongSphere_5</name>
			<color>
				<r>0.0</r>
				<g>0.3</g>
				<b>0.4</b>
			</color>
			<position>
				<x>190</x>
				<y>-20</y>
				<z>-420</z>
			</position>
			<rotation>
				<x>0.0</x>
				<y>0.0</y>
				<z>0.0</z>
			</rotation>
			<scale>
				<x>0.3</x>
				<y>0.3</y>
				<z>0.3</z>
			</scale>
			<lights>
				<light>1</light>
				<light>10</light>
				<light>100</light>
			</lights>
		</object>

		<object id="46">
			<model>5</model>
			<shader>12</shader>
			<type>normal</type>
			<name>PhongSphere_6</name>
			<color>
				<r>0.0</r>
				<g>0.3</g>
				<b>0.4</b>
			</color>
			<position>
				<x>190</x>
				<y>-20</y>
				<z>-470</z>
			</position>
			<rotation>
				<x>0.0</x>
				<y>0.0</y>
				<z>0.0</z>
			</rotation>
			<scale>
				<x>0.3</x>
				<y>0.3</y>
				<z>0.3</z>
			</scale>
			<lights>
				<light>1</light>
				<light>10</light>
				<light>100</light>
			</lights>
		</object>

		<object id="47">
			<model>5</model>
			<shader>12</shader>
			<type>normal</type>
			<name>PhongSphere_7</name>
			<color>
				<r>0.0</r>
				<g>0.1</g>
				<b>0.1</b>
			</color>
			<position>
				<x>280</x>
				<y>-20</y>
				<z>-520</z>
			</position>
			<rotation>
				<x>0.0</x>
				<y>0.0</y>
				<z>0.0</z>
			</rotation>
			<scale>
				<x>0.3</x>
				<y>0.3</y>
				<z>0.3</z>
			</scale>
			<lights>
				<light>1</light>
				<light>10</light>
				<light>100</light>
			</lights>
		</object>

		<object id="48">
			<model>5</model>
			<shader>14</shader>
			<type>normal</type>
			<name>ReflectionSphere_Partial</name>
			<textures>
				<texture id="20"/>
			</textures>
			<color>
				<r>0.1</r>
				<g>0.3</g>
				<b>0.1</b>
			</color>
			<position>
				<x>120</x>
				<y>-20</y>
				<z>-220</z>
			</position>
			<rotation>
				<x>0.0</x>
				<y>0.0</y>
				<z>0.0</z>
			</rotation>
			<scale>
				<x>0.3</x>
				<y>0.3</y>
				<z>0.3</z>
			</scale>
		</object>

		<object id="49">
			<model>5</model>
			<shader>15</shader>
			<type>normal</type>
			<name>ReflectionSphere_Total</name>
			<textures>
				<texture id="20"/>
			</textures>
			<position>
				<x>70</x>
				<y>-20</y>
				<z>-220</z>
			</position>
			<rotation>
				<x>0.0</x>
				<y>0.0</y>
				<z>0.0</z>
			</rotation>
			<scale>
				<x>0.3</x>
				<y>0.3</y>
				<z>0.3</z>
			</scale>
		</object>

		<object id="100">
			<model>generated</model>
			<shader>3</shader>
			<type>terrain</type>
			<name>Teren</name>
			<textures>
				<texture id="14"/>
				<texture id="15"/>
				<texture id="16"/>
				<texture id="17"/>
			</textures>
			<position>
				<x>0</x>
				<y>0</y>
				<z>0</z>
			</position>
			<rotation>
				<x>0.0</x>
				<y>0.0</y>
				<z>0.0</z>
			</rotation>
			<scale>
				<x>1.0</x>
				<y>1.0</y>
				<z>1.0</z>
			</scale>
			<height>
				<r>15</r>
				<g>5</g>
				<b>-5</b>
			</height>
		</object>

		<object id="101">
			<model>6</model>
			<shader>4</shader>
			<type>skybox</type>
			<name>Skybox</name>
			<textures>
				<texture id="20"/>
			</textures>
			<position>
				<x>0</x>
				<y>0</y>
				<z>0</z>
			</position>
			<rotation>
				<x>0</x>
				<y>0</y>
				<z>0</z>
			</rotation>
			<scale>
				<x>10000</x>
				<y>10000</y>
				<z>10000</z>
			</scale>
			<followingCamera>
				<ox/>
				<oz/>
			</followingCamera>
		</object>

		<object id="102">
			<model>7</model>
			<shader>5</shader>
			<type>fire</type>
			<name>Foc</name>
			<textures>
				<texture id="30"/>
				<texture id="31"/>
				<texture id="32"/>
			</textures>
			<position>
				<x>-100</x>
				<y>20</y>
				<z>-100</z>
			</position>
			<rotation>
				<x>0</x>
				<y>0</y>
				<z>0</z>
			</rotation>
			<scale>
				<x>10.0</x>
				<y>10.0</y>
				<z>10.0</z>
			</scale>
			<dispMax>0.13</dispMax>
		</object>

	</objects>
	
	
	<lights>
		
		<light id="1">
			<type>directional</type>

			<direction>
				<x>1.0</x>
				<y>-1.0</y>
				<z>0.0</z>
			</direction>

			<ambientColor>
				<r>1.0</r>
				<g>1.0</g>
				<b>1.0</b>
			</ambientColor>
			<diffuseColor>
				<r>1.0</r>
				<g>1.0</g>
				<b>1.0</b>
			</diffuseColor>
			<specularColor>
				<r>1.0</r>
				<g>1.0</g>
				<b>1.0</b>
			</specularColor>
		</light>

		<light id="10">
			<type>point</type>

			<position>
				<x>280</x>
				<y>-20</y>
				<z>-220</z>
			</position>

			<!-- max distance = 600 -->
			<constant>1.0</constant>
			<linear>0.007</linear>
			<quadratic>0.0002</quadratic>

			<ambientColor>
				<r>1.0</r>
				<g>1.0</g>
				<b>1.0</b>
			</ambientColor>
			<diffuseColor>
				<r>1.0</r>
				<g>1.0</g>
				<b>1.0</b>
			</diffuseColor>
			<specularColor>
				<r>1.0</r>
				<g>1.0</g>
				<b>1.0</b>
			</specularColor>
		</light>

		<light id="100">
			<type>spotlight</type>

			<position>
				<x>280</x>
				<y>-20</y>
				<z>-470</z>
			</position>
			<direction>
				<x>0.0</x>
				<y>0.0</y>
				<z>-1.0</z>
			</direction>

			<!-- max distance = 600 -->
			<constant>1.0</constant>
			<linear>0.007</linear>
			<quadratic>0.0002</quadratic>
			
			<cutOff>12.5</cutOff>
			<outerCutOff>15.0</outerCutOff>

			<ambientColor>
				<r>1.0</r>
				<g>1.0</g>
				<b>1.0</b>
			</ambientColor>
			<diffuseColor>
				<r>1.0</r>
				<g>1.0</g>
				<b>1.0</b>
			</diffuseColor>
			<specularColor>
				<r>1.0</r>
				<g>1.0</g>
				<b>1.0</b>
			</specularColor>
		</light>
		
	</lights>

	
	<debugSettings>
		<objectAxes>
			<OXColor>
				<r>1.0</r>
				<g>0.0</g>
				<b>0.0</b>
			</OXColor>
			<OYColor>
				<r>0.0</r>
				<g>1.0</g>
				<b>0.0</b>
			</OYColor>
			<OZColor>
				<r>0.0</r>
				<g>0.0</g>
				<b>1.0</b>
			</OZColor>
		</objectAxes>
		<camAxes>
			<OXColor>
				<r>1.0</r>
				<g>1.0</g>
				<b>0.0</b>
			</OXColor>
			<OYColor>
				<r>0.0</r>
				<g>1.0</g>
				<b>1.0</b>
			</OYColor>
			<OZColor>
				<r>1.0</r>
				<g>0.0</g>
				<b>1.0</b>
			</OZColor>
		</camAxes>
	</debugSettings>
	
</sceneManager>

